pcapy.cpython-310-darwin.so
pcapy_ng_macos-1.0.4.data/data/share/doc/pcapy-ng-macos/LICENSE
pcapy_ng_macos-1.0.4.data/data/share/doc/pcapy-ng-macos/README
pcapy_ng_macos-1.0.4.data/data/share/doc/pcapy-ng-macos/pcapy.html
pcapy_ng_macos-1.0.4.data/data/share/doc/pcapy-ng-macos/tests/96pings.pcap
pcapy_ng_macos-1.0.4.data/data/share/doc/pcapy-ng-macos/tests/pcapytests.py
pcapy_ng_macos-1.0.4.dist-info/LICENSE
pcapy_ng_macos-1.0.4.dist-info/METADATA
pcapy_ng_macos-1.0.4.dist-info/WHEEL
pcapy_ng_macos-1.0.4.dist-info/top_level.txt
pcapy_ng_macos-1.0.4.dist-info/RECORD
